Workbook

Sheet 1.指标假设
A1: 财务模型
A3: 装机量
B4: Y1 | C4: Y2 | D4: Y3
A5: 年末累计装机（户） | B5: 1000 | C5: 5000 | D5: 15000
A7: SKU 定价与降本路线
B8: 尝鲜 | C8: 全屋S | D8: 全屋L
A9: 零售价（元） | B9: 299 | C9: 499 | D9: 799
A10: 初期 BOM（元）Y1 | B10: 170 | C10: 320 | D10: 620
A11: 销量占比 | B11: 0.1 | C11: 0.5 | D11: 0.4
A12: 加权 ASP（元） | B12: =SUMPRODUCT(B9:D9,B11:D11) -> 599
A13: 加权 BOM Y1（元） | B13: =SUMPRODUCT(B10:D10,B11:D11) -> 425
A14: 降本后加权 BOM（元/台） | B14: 425 | C14: 100 | D14: 60
A15: 单台硬件毛利（元） | B15: =B12-B14 -> 174 | C15: =B12-C14 -> 499 | D15: =B12-D14 -> 539
A16: 硬件毛利率 | B16: =B15/B12 -> 0.29048414 | C16: =C15/B12 -> 0.83305509 | D16: =D15/B12 -> 0.89983306
A18: 订阅参数
A19: 参数 | B19: 值
A20: 订阅价（元/年） | B20: 199
A21: 转化率 | B21: 0.2
A22: 续费率 | B22: 0.7
A23: 云免费层（元/户/年） | B23: 12
A24: 云付费层（元/户/年） | B24: 45
A25: CAC早期（元） | B25: 300
A26: CAC降本后（元） | B26: 250
A28: 费用驱动参数
A29: 参数 | B29: Y1 | C29: Y2 | D29: Y3
A30: 团队人数（不含创始人） | B30: 5 | C30: 8 | D30: 12
A31: 人均年薪（万元） | B31: 30 | C31: 30 | D31: 30
A32: 创始人年薪（万元） | B32: 25 | C32: 30 | D32: 35
A33: 人力合计（万元） | B33: =B30*B31+B32 -> 175 | C33: =C30*C31+C32 -> 270 | D33: =D30*D31+D32 -> 395
A34: 办公行政（万元） | B34: 20 | C34: 30 | D34: 50
A35: GPU 云月费（万元） | B35: 0.8 | C35: 4 | D35: 8
A36: DB 云月费（万元） | B36: 0.25 | C36: 0.8 | D36: 1.7
A37: 设备采购（万元） | B37: 10 | C37: 30 | D37: 40

Sheet 2.销售与收入
A1: 销售与收入
A3: 硬件收入
B4: Y1 | C4: Y2 | D4: Y3
A5: 累计装机（户） | B5: ='1.指标假设'!B5 -> 1000 | C5: ='1.指标假设'!C5 -> 5000 | D5: ='1.指标假设'!D5 -> 15000
A6: 新增装机（户） | B6: =B5 -> 1000 | C6: =C5-B5 -> 4000 | D6: =D5-C5 -> 10000
A7: 加权 ASP（元） | B7: ='1.指标假设'!B12 -> 599 | C7: ='1.指标假设'!B12 -> 599 | D7: ='1.指标假设'!B12 -> 599
A8: 硬件收入（万元） | B8: =B6*B7/10000 -> 59.9 | C8: =C6*C7/10000 -> 239.6 | D8: =D6*D7/10000 -> 599
A10: 订阅收入
B11: Y1 | C11: Y2 | D11: Y3
A12: 新增订阅户 | B12: =B6*'1.指标假设'!B21 -> 200 | C12: =C6*'1.指标假设'!B21 -> 800 | D12: =D6*'1.指标假设'!B21 -> 2000
A13: 续费订阅户 | B13: 0 | C13: =B14*'1.指标假设'!B22 -> 140 | D13: =C14*'1.指标假设'!B22 -> 658
A14: 活跃订阅户 | B14: =B12+B13 -> 200 | C14: =C12+C13 -> 940 | D14: =D12+D13 -> 2658
A15: 订阅价（元/年） | B15: ='1.指标假设'!B20 -> 199 | C15: ='1.指标假设'!B20 -> 199 | D15: ='1.指标假设'!B20 -> 199
A16: 订阅收入（万元） | B16: =B14*B15/10000 -> 3.98 | C16: =C14*C15/10000 -> 18.706 | D16: =D14*D15/10000 -> 52.8942
A18: 总收入（万元） | B18: =B8+B16 -> 63.88 | C18: =C8+C16 -> 258.306 | D18: =D8+D16 -> 651.8942

Sheet 3.成本费用
A1: 成本费用
A3: 营业成本
B4: Y1 | C4: Y2 | D4: Y3
A5: 加权 BOM（元） | B5: ='1.指标假设'!B14 -> 425 | C5: ='1.指标假设'!C14 -> 100 | D5: ='1.指标假设'!D14 -> 60
A6: 新增装机（户） | B6: ='2.销售与收入'!B6 -> 1000 | C6: ='2.销售与收入'!C6 -> 4000 | D6: ='2.销售与收入'!D6 -> 10000
A7: 硬件 BOM 成本（万元） | B7: =B5*B6/10000 -> 42.5 | C7: =C5*C6/10000 -> 40 | D7: =D5*D6/10000 -> 60
A8: 活跃订阅户 | B8: ='2.销售与收入'!B14 -> 200 | C8: ='2.销售与收入'!C14 -> 940 | D8: ='2.销售与收入'!D14 -> 2658
A9: 累计装机（户） | B9: ='2.销售与收入'!B5 -> 1000 | C9: ='2.销售与收入'!C5 -> 5000 | D9: ='2.销售与收入'!D5 -> 15000
A10: 免费用户数 | B10: =B9-B8 -> 800 | C10: =C9-C8 -> 4060 | D10: =D9-D8 -> 12342
A11: 云成本合计（万元） | B11: =(B10*'1.指标假设'!B23+B8*'1.指标假设'!B24)/10000 -> 1.86 | C11: =(C10*'1.指标假设'!B23+C8*'1.指标假设'!B24)/10000 -> 9.102 | D11: =(D10*'1.指标假设'!B23+D8*'1.指标假设'!B24)/10000 -> 26.7714
A12: 营业成本合计（万元） | B12: =B7+B11 -> 44.36 | C12: =C7+C11 -> 49.102 | D12: =D7+D11 -> 86.7714
A14: 运营费用
B15: Y1 | C15: Y2 | D15: Y3
A16: 人力成本 | B16: ='1.指标假设'!B33 -> 175 | C16: ='1.指标假设'!C33 -> 270 | D16: ='1.指标假设'!D33 -> 395
A17: 办公行政 | B17: ='1.指标假设'!B34 -> 20 | C17: ='1.指标假设'!C34 -> 30 | D17: ='1.指标假设'!D34 -> 50
A18: GPU云（月费x12） | B18: ='1.指标假设'!B35*12 -> 9.6 | C18: ='1.指标假设'!C35*12 -> 48 | D18: ='1.指标假设'!D35*12 -> 96
A19: DB云（月费x12） | B19: ='1.指标假设'!B36*12 -> 3 | C19: ='1.指标假设'!C36*12 -> 9.6 | D19: ='1.指标假设'!D36*12 -> 20.4
A20: 设备采购 | B20: ='1.指标假设'!B37 -> 10 | C20: ='1.指标假设'!C37 -> 30 | D20: ='1.指标假设'!D37 -> 40
A21: 运营费用合计（万元） | B21: =SUM(B16:B20) -> 217.6 | C21: =SUM(C16:C20) -> 387.6 | D21: =SUM(D16:D20) -> 601.4

Sheet 4.利润表
A1: 利润表（万元）
B3: Y1 | C3: Y2 | D3: Y3
A4: 硬件收入 | B4: ='2.销售与收入'!B8 -> 59.9 | C4: ='2.销售与收入'!C8 -> 239.6 | D4: ='2.销售与收入'!D8 -> 599
A5: 订阅收入 | B5: ='2.销售与收入'!B16 -> 3.98 | C5: ='2.销售与收入'!C16 -> 18.706 | D5: ='2.销售与收入'!D16 -> 52.8942
A6: 总收入 | B6: =B4+B5 -> 63.88 | C6: =C4+C5 -> 258.306 | D6: =D4+D5 -> 651.8942
A7: 营业成本 | B7: ='3.成本费用'!B12 -> 44.36 | C7: ='3.成本费用'!C12 -> 49.102 | D7: ='3.成本费用'!D12 -> 86.7714
A8: 毛利 | B8: =B6-B7 -> 19.52 | C8: =C6-C7 -> 209.204 | D8: =D6-D7 -> 565.1228
A9: 毛利率 | B9: =B8/B6 -> 0.30557295 | C9: =C8/C6 -> 0.80990763 | D9: =D8/D6 -> 0.86689343
A10: 运营费用 | B10: ='3.成本费用'!B21 -> 217.6 | C10: ='3.成本费用'!C21 -> 387.6 | D10: ='3.成本费用'!D21 -> 601.4
A11: 净利润 | B11: =B8-B10 -> -198.08 | C11: =C8-C10 -> -178.396 | D11: =D8-D10 -> -36.2772
A12: 净利率 | B12: =B11/B6 -> -3.100814 | C12: =C11/C6 -> -0.69063824 | D12: =D11/D6 -> -0.055648907

Sheet 5.单位经济
A1: 单位经济
A3: LTV / CAC
B4: 降本前 (BOM 425) | C4: 降本后 (BOM 100)
A5: 硬件 ASP（元） | B5: 599 | C5: 599
A6: 硬件 BOM（元） | B6: 425 | C6: 100
A7: 单台毛利（元） | B7: =B5-B6 -> 174 | C7: =C5-C6 -> 499
A8: 订阅 ARPU（元/年） | B8: =199*0.2 -> 39.8 | C8: =199*0.2 -> 39.8
A9: 3年订阅 LTV（元） | B9: =B8*(1+0.7+0.49) -> 87.162 | C9: =C8*(1+0.7+0.49) -> 87.162
A10: 3年总 LTV（元） | B10: =B7+B9 -> 261.162 | C10: =C7+C9 -> 586.162
A11: CAC（元） | B11: 300 | C11: 250
A12: LTV / CAC | B12: =B10/B11 -> 0.87054 | C12: =C10/C11 -> 2.344648
A14: 敏感性：转化率对 LTV/CAC 的影响
A15: 转化率 | B15: 订阅 LTV（元） | C15: 降本前 LTV/CAC | D15: 降本后 LTV/CAC
A16: 0.1 | B16: 44 | C16: =(174+B16)/300 -> 0.72666667 | D16: =(499+B16)/250 -> 2.172
A17: 0.2 | B17: 87 | C17: =(174+B17)/300 -> 0.87 | D17: =(499+B17)/250 -> 2.344
A18: 0.3 | B18: 131 | C18: =(174+B18)/300 -> 1.0166667 | D18: =(499+B18)/250 -> 2.52
